LICENSE.md
MANIFEST.in
README.md
setup.py
django_rest_framework_simplify.egg-info/PKG-INFO
django_rest_framework_simplify.egg-info/SOURCES.txt
django_rest_framework_simplify.egg-info/dependency_links.txt
django_rest_framework_simplify.egg-info/requires.txt
django_rest_framework_simplify.egg-info/top_level.txt
rest_framework_simplify/__init__.py
rest_framework_simplify/apps.py
rest_framework_simplify/decorators.py
rest_framework_simplify/errors.py
rest_framework_simplify/exceptions.py
rest_framework_simplify/fields.py
rest_framework_simplify/forms.py
rest_framework_simplify/handler.py
rest_framework_simplify/helpers.py
rest_framework_simplify/mapper.py
rest_framework_simplify/models.py
rest_framework_simplify/serializer.py
rest_framework_simplify/signature.py
rest_framework_simplify/views.py
rest_framework_simplify/services/__init__.py
rest_framework_simplify/services/sql_executor/__init__.py
rest_framework_simplify/services/sql_executor/exceptions.py
rest_framework_simplify/services/sql_executor/service.py
rest_framework_simplify/services/sql_executor/tests.py