Metadata-Version: 2.1
Name: django-rest-framework-simplify
Version: 4.0.5.dev1
Summary: Django Rest Framework Simplify
Home-page: https://github.com/Skylude/django-rest-framework-simplify
Author: Skyler Cain
Author-email: skylercain@gmail.com
License-File: LICENSE.md
